text_help/__init__.py
text_help-1.0.2.dist-info/WHEEL
text_help-1.0.2.dist-info/METADATA
text_help-1.0.2.dist-info/RECORD
